{
    "project_hash": "f653a372-28ef-4a51-8a7b-60b7af9433f0",
    "components": {
        "button": {
            "installationTime": 1774522281
        },
        "icon": {
            "installationTime": 1774522320
        },
        "card": {
            "installationTime": 1774522321
        },
        "input": {
            "installationTime": 1774522321
        },
        "badge": {
            "installationTime": 1774522322
        },
        "heading": {
            "installationTime": 1774522322
        },
        "text": {
            "installationTime": 1774522322
        },
        "separator": {
            "installationTime": 1774522323
        },
        "avatar": {
            "installationTime": 1774522344
        },
        "dropdown": {
            "installationTime": 1774522344
        },
        "label": {
            "installationTime": 1774522344
        },
        "link": {
            "installationTime": 1774522345
        },
        "field": {
            "installationTime": 1774522345
        }
    }
}